LICENSE
MANIFEST.in
README.md
requirements.txt
setup.py
pyauto/__init__.py
pyauto.sitemap.egg-info/PKG-INFO
pyauto.sitemap.egg-info/SOURCES.txt
pyauto.sitemap.egg-info/dependency_links.txt
pyauto.sitemap.egg-info/requires.txt
pyauto.sitemap.egg-info/top_level.txt
pyauto/sitemap/__init__.py
pyauto/sitemap/commands.py
pyauto/sitemap/config.py
pyauto/sitemap/parser.py