Metadata-Version: 1.0
Name: pyauto.sitemap
Version: 0.0.1a1
Summary: Tools for parsing sitemaps
Home-page: https://github.com/adamjaso/pyauto/tree/master/sitemap
Author: Adam Jaso
Author-email: UNKNOWN
License: GNU General Public License V2
Platform: UNKNOWN
